docs/__init__.py
examples/__init__.py
examples/basic_usage.py
examples/chatbot.py
examples/code_assistant.py
examples/multi_provider.py
stonechain-1.0.0.dist-info/licenses/LICENSE
tests/__init__.py
tests/test_simplechain.py
tests/test_stonechain.py
workflows/__init__.py
workflows/benchmark.py
workflows/stonechain.py
workflows/stonechain_mcp.py
workflows/stonechain_mcp_server.py
workflows/stonechain_vectors.py
workflows/docs/__init__.py
workflows/examples/__init__.py
workflows/examples/basic_usage.py
workflows/examples/chatbot.py
workflows/examples/code_assistant.py
workflows/examples/multi_provider.py
workflows/tests/__init__.py
workflows/tests/test_stonechain.py
stonechain-1.0.0.dist-info/METADATA
stonechain-1.0.0.dist-info/WHEEL
stonechain-1.0.0.dist-info/entry_points.txt
stonechain-1.0.0.dist-info/top_level.txt
stonechain-1.0.0.dist-info/RECORD
