Metadata-Version: 2.4
Name: stonechain
Version: 1.0.0
Summary: Zero-dependency LLM framework. LangChain in 800 lines. Built like a rock.
Author-email: Kent Stone <kent@stoneresearch.ai>
Maintainer-email: Kent Stone <kent@stoneresearch.ai>
License-Expression: MIT
Project-URL: Homepage, https://github.com/KentStone/stonechain
Project-URL: Documentation, https://github.com/KentStone/stonechain#readme
Project-URL: Repository, https://github.com/KentStone/stonechain
Project-URL: Issues, https://github.com/KentStone/stonechain/issues
Keywords: llm,langchain,ai,openai,anthropic,claude,gpt,chatgpt,ollama,groq,mistral,deepseek,chain,agent,rag,zero-dependency
Classifier: Development Status :: 5 - Production/Stable
Classifier: Intended Audience :: Developers
Classifier: Operating System :: OS Independent
Classifier: Programming Language :: Python :: 3
Classifier: Programming Language :: Python :: 3.8
Classifier: Programming Language :: Python :: 3.9
Classifier: Programming Language :: Python :: 3.10
Classifier: Programming Language :: Python :: 3.11
Classifier: Programming Language :: Python :: 3.12
Classifier: Programming Language :: Python :: 3.13
Classifier: Topic :: Scientific/Engineering :: Artificial Intelligence
Classifier: Topic :: Software Development :: Libraries :: Python Modules
Requires-Python: >=3.8
License-File: LICENSE
Provides-Extra: dev
Requires-Dist: pytest>=7.0; extra == "dev"
Requires-Dist: pytest-asyncio>=0.21; extra == "dev"
Dynamic: license-file
